human_readable/__init__.py
human_readable/files.py
human_readable/i18n.py
human_readable/lists.py
human_readable/numbers.py
human_readable/py.typed
human_readable/times.py
human_readable/locale/de_DE/LC_MESSAGES/human_readable.mo
human_readable/locale/de_DE/LC_MESSAGES/human_readable.po
human_readable/locale/en_ABBR/LC_MESSAGES/human_readable.mo
human_readable/locale/en_ABBR/LC_MESSAGES/human_readable.po
human_readable/locale/es_ES/LC_MESSAGES/human_readable.mo
human_readable/locale/es_ES/LC_MESSAGES/human_readable.po
human_readable/locale/fa_IR/LC_MESSAGES/human_readable.mo
human_readable/locale/fa_IR/LC_MESSAGES/human_readable.po
human_readable/locale/fi_FI/LC_MESSAGES/human_readable.mo
human_readable/locale/fi_FI/LC_MESSAGES/human_readable.po
human_readable/locale/fr_FR/LC_MESSAGES/human_readable.mo
human_readable/locale/fr_FR/LC_MESSAGES/human_readable.po
human_readable/locale/id_ID/LC_MESSAGES/human_readable.mo
human_readable/locale/id_ID/LC_MESSAGES/human_readable.po
human_readable/locale/it_IT/LC_MESSAGES/human_readable.mo
human_readable/locale/it_IT/LC_MESSAGES/human_readable.po
human_readable/locale/ja_JP/LC_MESSAGES/human_readable.mo
human_readable/locale/ja_JP/LC_MESSAGES/human_readable.po
human_readable/locale/ko_KR/LC_MESSAGES/human_readable.mo
human_readable/locale/ko_KR/LC_MESSAGES/human_readable.po
human_readable/locale/nl_NL/LC_MESSAGES/human_readable.mo
human_readable/locale/nl_NL/LC_MESSAGES/human_readable.po
human_readable/locale/pl_PL/LC_MESSAGES/human_readable.mo
human_readable/locale/pl_PL/LC_MESSAGES/human_readable.po
human_readable/locale/pt_BR/LC_MESSAGES/human_readable.mo
human_readable/locale/pt_BR/LC_MESSAGES/human_readable.po
human_readable/locale/pt_PT/LC_MESSAGES/human_readable.mo
human_readable/locale/pt_PT/LC_MESSAGES/human_readable.po
human_readable/locale/ru_RU/LC_MESSAGES/human_readable.mo
human_readable/locale/ru_RU/LC_MESSAGES/human_readable.po
human_readable/locale/sk_SK/LC_MESSAGES/human_readable.mo
human_readable-2.0.0.dist-info/METADATA
human_readable-2.0.0.dist-info/WHEEL
human_readable-2.0.0.dist-info/licenses/LICENSE
human_readable-2.0.0.dist-info/RECORD
