Metadata-Version: 2.4
Name: human-readable
Version: 2.0.0
Summary: Human Readable
Project-URL: homepage, https://github.com/staticdev/human-readable
Project-URL: repository, https://github.com/staticdev/human-readable
Project-URL: documentation, https://human-readable.readthedocs.io
Project-URL: changelog, https://github.com/staticdev/human-readable/releases
Author-email: staticdev <staticdev-support@proton.me>
License: MIT
License-File: LICENSE
Classifier: Development Status :: 5 - Production/Stable
Classifier: Programming Language :: Python :: 3.9
Classifier: Programming Language :: Python :: 3.10
Classifier: Programming Language :: Python :: 3.11
Classifier: Programming Language :: Python :: 3.12
Classifier: Programming Language :: Python :: 3.13
Requires-Python: >=3.9
